bitmoro/__init__.py
bitmoro/bitmoro.py
bitmoro/test.py
bitmoro_sms-1.0.1.dist-info/LICENSE.txt
bitmoro_sms-1.0.1.dist-info/METADATA
bitmoro_sms-1.0.1.dist-info/WHEEL
bitmoro_sms-1.0.1.dist-info/top_level.txt
bitmoro_sms-1.0.1.dist-info/RECORD
